mexe.py
mexe-0.0.1.dist-info/RECORD
mexe-0.0.1.dist-info/METADATA
mexe-0.0.1.dist-info/top_level.txt
mexe-0.0.1.dist-info/metadata.json
mexe-0.0.1.dist-info/WHEEL
mexe-0.0.1.dist-info/entry_points.txt
mexe-0.0.1.dist-info/DESCRIPTION.rst
