Metadata-Version: 2.0
Name: mexe
Version: 0.0.1
Summary: a script for making .py files executable
Home-page: https://github.com/SanketDG/mexe
Author: Sanket Dasgupta
Author-email: sanketdasgupta@gmail.com
License: MIT
Platform: UNKNOWN
